{
    "COST": {
        "gamma": 20450654.242951877,
        "vanna": 12589006390.35978,
        "spot": 525.3,
        "last_update": "2026-05-15T18:20:36Z"
    },
    "LMT": {
        "gamma": 7209276.750985653,
        "vanna": 1140971477.122036,
        "spot": 215.61,
        "last_update": "2026-05-15T18:20:36Z"
    },
    "KTOS": {
        "gamma": 3925771.5701537332,
        "vanna": 5610138.681092808,
        "spot": 27.5,
        "last_update": "2026-05-15T18:20:36Z"
    },
    "NIO": {
        "gamma": 154832603.46557194,
        "vanna": 4115642.086680091,
        "spot": 5.3,
        "last_update": "2026-05-15T18:20:36Z"
    },
    "RTX": {
        "gamma": 26848148.607275605,
        "vanna": 385529266.50292146,
        "spot": 124.0,
        "last_update": "2026-05-15T18:20:36Z"
    },
    "LHX": {
        "gamma": 0.0,
        "vanna": 0.0,
        "spot": NaN,
        "last_update": "2026-05-15T18:20:36Z"
    },
    "TXN": {
        "gamma": 17852767.894425116,
        "vanna": 147340582.04223162,
        "spot": 223.0,
        "last_update": "2026-05-15T18:20:36Z"
    },
    "NOW": {
        "gamma": 50637844.89204594,
        "vanna": 285912634.00186217,
        "spot": 44.32,
        "last_update": "2026-05-15T18:20:37Z"
    },
    "HIMS": {
        "gamma": 53672465.42529452,
        "vanna": 12989821.447921377,
        "spot": 21.05,
        "last_update": "2026-05-15T18:20:37Z"
    },
    "COIN": {
        "gamma": 79104352.46063177,
        "vanna": 1772269263.6205578,
        "spot": 213.79,
        "last_update": "2026-05-15T18:20:37Z"
    },
    "NVDA": {
        "gamma": 1278050805.8653157,
        "vanna": 17660824314.418106,
        "spot": 218.52,
        "last_update": "2026-05-15T18:20:37Z"
    },
    "SNDK": {
        "gamma": 19221298.443973266,
        "vanna": -9689325464.937763,
        "spot": 1117.1,
        "last_update": "2026-05-15T18:20:37Z"
    },
    "MSTR": {
        "gamma": 134785684.45869172,
        "vanna": 2130941545.5901654,
        "spot": 175.5,
        "last_update": "2026-05-15T18:20:37Z"
    },
    "MU": {
        "gamma": 125114521.60673554,
        "vanna": -1659784354.7685566,
        "spot": 768.04,
        "last_update": "2026-05-15T18:20:37Z"
    },
    "TSLA": {
        "gamma": 556237744.538827,
        "vanna": 74836608920.13141,
        "spot": 442.8,
        "last_update": "2026-05-15T18:20:37Z"
    },
    "NET": {
        "gamma": 14819895.95163493,
        "vanna": 235132972.55358034,
        "spot": 107.98,
        "last_update": "2026-05-15T18:20:37Z"
    },
    "AAPL": {
        "gamma": 819336392.3816876,
        "vanna": 22040392165.2082,
        "spot": 292.93,
        "last_update": "2026-05-15T18:20:37Z"
    },
    "AMZN": {
        "gamma": 387803977.9975544,
        "vanna": 14906584292.187866,
        "spot": 162.78,
        "last_update": "2026-05-15T18:20:37Z"
    },
    "MSFT": {
        "gamma": 267917006.1286103,
        "vanna": 43545466825.70448,
        "spot": 194.47,
        "last_update": "2026-05-15T18:20:37Z"
    },
    "CRM": {
        "gamma": 45255685.87302598,
        "vanna": 800662331.7649472,
        "spot": 83.0,
        "last_update": "2026-05-15T18:20:37Z"
    },
    "META": {
        "gamma": 337921071.0950098,
        "vanna": 127905872478.5494,
        "spot": 612.7,
        "last_update": "2026-05-15T18:20:37Z"
    },
    "RKLB": {
        "gamma": 29849573.52241938,
        "vanna": -151898920.33171114,
        "spot": 95.89,
        "last_update": "2026-05-15T18:20:37Z"
    },
    "ALAB": {
        "gamma": 8397833.028294673,
        "vanna": -4460854.855848148,
        "spot": 160.84,
        "last_update": "2026-05-15T18:20:37Z"
    },
    "CRDO": {
        "gamma": 9733776.671503497,
        "vanna": 51530312.054381356,
        "spot": 139.58,
        "last_update": "2026-05-15T18:20:37Z"
    },
    "PLTR": {
        "gamma": 252756167.73142117,
        "vanna": 3337903581.830921,
        "spot": 104.95,
        "last_update": "2026-05-15T18:20:37Z"
    },
    "GOOG": {
        "gamma": 127600738.6351104,
        "vanna": 2663825170.4977455,
        "spot": 236.02,
        "last_update": "2026-05-15T18:20:37Z"
    },
    "AVGO": {
        "gamma": 131569752.38807878,
        "vanna": 9173784859.744793,
        "spot": 311.3,
        "last_update": "2026-05-15T18:20:37Z"
    },
    "BE": {
        "gamma": 24206826.300430097,
        "vanna": -115574982.52666666,
        "spot": 248.81,
        "last_update": "2026-05-15T18:20:37Z"
    },
    "GEV": {
        "gamma": 13611241.658552289,
        "vanna": 4524586186.932982,
        "spot": 874.78,
        "last_update": "2026-05-15T18:20:37Z"
    },
    "GLD": {
        "gamma": 439800535.56162256,
        "vanna": 63648980956.94188,
        "spot": 240.34,
        "last_update": "2026-05-15T18:20:38Z"
    },
    "SLV": {
        "gamma": 593808017.3005675,
        "vanna": 1187437928.5836265,
        "spot": 56.52,
        "last_update": "2026-05-15T18:20:38Z"
    },
    "APP": {
        "gamma": 12701245.289514337,
        "vanna": 1379427199.3916056,
        "spot": 300.37,
        "last_update": "2026-05-15T18:20:38Z"
    },
    "TEM": {
        "gamma": 15783335.307664454,
        "vanna": 17516544.59384839,
        "spot": 29.0,
        "last_update": "2026-05-15T18:20:38Z"
    },
    "VST": {
        "gamma": 19475904.825333603,
        "vanna": 217918707.6233657,
        "spot": 62.35,
        "last_update": "2026-05-15T18:20:38Z"
    },
    "ISRG": {
        "gamma": 4486360.505728273,
        "vanna": 518856474.33318686,
        "spot": 119.99,
        "last_update": "2026-05-15T18:20:38Z"
    },
    "SATS": {
        "gamma": 27172413.0121769,
        "vanna": 10770830.578751411,
        "spot": 71.9,
        "last_update": "2026-05-15T18:20:38Z"
    },
    "ASTS": {
        "gamma": 49874039.67610515,
        "vanna": 12782036.975030253,
        "spot": 62.75,
        "last_update": "2026-05-15T18:20:38Z"
    },
    "ORCL": {
        "gamma": 113314190.34982052,
        "vanna": 3524518489.8994317,
        "spot": 121.37,
        "last_update": "2026-05-15T18:20:38Z"
    },
    "IREN": {
        "gamma": 72138906.91267806,
        "vanna": 29484381.495719336,
        "spot": 40.89,
        "last_update": "2026-05-15T18:20:38Z"
    },
    "CRWV": {
        "gamma": 80141280.50483271,
        "vanna": 405228011.5285942,
        "spot": 67.67,
        "last_update": "2026-05-15T18:20:38Z"
    },
    "AMD": {
        "gamma": 141695420.50261387,
        "vanna": -399178955.2019405,
        "spot": 427.2,
        "last_update": "2026-05-15T18:20:38Z"
    },
    "LLY": {
        "gamma": 18421701.405894846,
        "vanna": 12857220399.652214,
        "spot": 492.38,
        "last_update": "2026-05-15T18:20:38Z"
    },
    "FIG": {
        "gamma": 20774988.00241911,
        "vanna": 3439474.022531727,
        "spot": 17.82,
        "last_update": "2026-05-15T18:20:38Z"
    },
    "ADI": {
        "gamma": 0.0,
        "vanna": 0.0,
        "spot": NaN,
        "last_update": "2026-05-15T18:20:38Z"
    },
    "WDC": {
        "gamma": 14791082.143040763,
        "vanna": 431919943.37386024,
        "spot": 344.71,
        "last_update": "2026-05-15T18:20:38Z"
    },
    "CEG": {
        "gamma": 0.0,
        "vanna": 0.0,
        "spot": NaN,
        "last_update": "2026-05-15T18:20:38Z"
    },
    "ANET": {
        "gamma": 21355028.160495404,
        "vanna": 188005096.62550312,
        "spot": 78.82,
        "last_update": "2026-05-15T18:20:38Z"
    },
    "SPY": {
        "gamma": 2180400097.8004203,
        "vanna": 687354461229.4763,
        "spot": 389.09,
        "last_update": "2026-05-15T18:20:38Z"
    },
    "QQQ": {
        "gamma": 1237889764.3362746,
        "vanna": 296811662246.8544,
        "spot": 399.93,
        "last_update": "2026-05-15T18:20:38Z"
    },
    "XOM": {
        "gamma": 81945742.92316368,
        "vanna": 691063534.9985063,
        "spot": 92.39,
        "last_update": "2026-05-15T18:20:38Z"
    },
    "TSM": {
        "gamma": 133595498.31069669,
        "vanna": 10451938155.691803,
        "spot": 313.08,
        "last_update": "2026-05-15T18:20:39Z"
    },
    "ARM": {
        "gamma": 17367111.094963722,
        "vanna": 47672881.80609065,
        "spot": 88.98,
        "last_update": "2026-05-15T18:20:39Z"
    },
    "ABBV": {
        "gamma": 16326213.146508638,
        "vanna": 619422580.1030738,
        "spot": 88.06,
        "last_update": "2026-05-15T18:20:39Z"
    },
    "JPM": {
        "gamma": 62356243.88540717,
        "vanna": 4471371880.495161,
        "spot": 156.71,
        "last_update": "2026-05-15T18:20:39Z"
    },
    "V": {
        "gamma": 37189181.923848644,
        "vanna": 2972501919.054308,
        "spot": 153.92,
        "last_update": "2026-05-15T18:20:39Z"
    },
    "MA": {
        "gamma": 13009082.76364321,
        "vanna": 2096584293.6125958,
        "spot": 213.48,
        "last_update": "2026-05-15T18:20:39Z"
    },
    "BAC": {
        "gamma": 213504245.20664132,
        "vanna": 440933716.2678029,
        "spot": 24.8,
        "last_update": "2026-05-15T18:20:39Z"
    },
    "SPGI": {
        "gamma": 0.0,
        "vanna": 0.0,
        "spot": NaN,
        "last_update": "2026-05-15T18:20:39Z"
    },
    "MS": {
        "gamma": 26746697.44442689,
        "vanna": 696214147.6031342,
        "spot": 114.08,
        "last_update": "2026-05-15T18:20:39Z"
    },
    "GS": {
        "gamma": 28774398.513336144,
        "vanna": 23574795007.100384,
        "spot": 602.84,
        "last_update": "2026-05-15T18:20:39Z"
    },
    "C": {
        "gamma": 92346280.5033663,
        "vanna": 900680354.392338,
        "spot": 80.76,
        "last_update": "2026-05-15T18:20:39Z"
    }
}